mircheck/__init__.py
mircheck/country-list.json
mircheck/mircheck.py
mircheck-1.1.4.dist-info/LICENSE
mircheck-1.1.4.dist-info/METADATA
mircheck-1.1.4.dist-info/WHEEL
mircheck-1.1.4.dist-info/entry_points.txt
mircheck-1.1.4.dist-info/top_level.txt
mircheck-1.1.4.dist-info/RECORD
