Metadata-Version: 2.1
Name: mircheck
Version: 1.1.4
Summary: A tool to find the fastest mirror for Ubuntu and its derivatives
Home-page: https://github.com/arkrwn/mircheck
Author: Arie Kurniawan
Author-email: hubungi.aja@gmail.com
Classifier: Programming Language :: Python :: 3
Classifier: License :: OSI Approved :: MIT License
Classifier: Operating System :: OS Independent
Requires-Python: >=3.6
License-File: LICENSE
Requires-Dist: requests
